{
  "depth": {
    "elements": {
      "position": {
        "outter": {
          "$type": "other",
          "$value": "dropShadow"
        },
        "inner": {
          "$type": "other",
          "$value": "innerShadow"
        }
      },
      "distance": {
        "flat": {
          "$type": "other",
          "$value": "0"
        },
        "micro": {
          "$type": "other",
          "$value": "{semantic.dimension.sizing.micro}"
        },
        "extraSmall": {
          "$type": "other",
          "$value": "{semantic.dimension.sizing.extraSmall}"
        },
        "small": {
          "$type": "other",
          "$value": "{semantic.dimension.sizing.small}"
        },
        "medium": {
          "$type": "other",
          "$value": "{semantic.dimension.sizing.medium}"
        },
        "large": {
          "$type": "other",
          "$value": "{semantic.dimension.sizing.large}"
        },
        "extraLarge": {
          "$type": "other",
          "$value": "{semantic.dimension.sizing.extraLarge}"
        },
        "mega": {
          "$type": "other",
          "$value": "{semantic.dimension.sizing.mega}"
        },
        "giga": {
          "$type": "other",
          "$value": "{semantic.dimension.sizing.giga}"
        }
      },
      "intensity": {
        "low": {
          "$type": "other",
          "$value": "0.05"
        },
        "medium": {
          "$type": "other",
          "$value": "0.15"
        },
        "high": {
          "$type": "other",
          "$value": "0.3"
        }
      },
      "proximity": {
        "distant": {
          "$type": "other",
          "$value": "-{semantic.dimension.sizing.extraSmall}"
        },
        "medium": {
          "$type": "other",
          "$value": "-{semantic.dimension.sizing.micro}"
        },
        "close": {
          "$type": "other",
          "$value": "-{semantic.dimension.sizing.nano}"
        },
        "flat": {
          "$type": "other",
          "$value": "0"
        }
      },
      "luminosity": {
        "shadow": {
          "deep": {
            "$type": "other",
            "$value": "{semantic.color.brand.ambient.grayscale.highest}"
          },
          "regular": {
            "$type": "other",
            "$value": "{semantic.color.brand.ambient.grayscale.mid}"
          },
          "smooth": {
            "$type": "other",
            "$value": "{semantic.color.brand.ambient.grayscale.lower}"
          }
        },
        "light": {
          "bright": {
            "$type": "other",
            "$value": "{semantic.color.brand.ambient.contrast.deep.background}"
          },
          "primary": {
            "$type": "other",
            "$value": "{semantic.color.interface.function.primary.normal.background}"
          },
          "info": {
            "$type": "other",
            "$value": "{semantic.color.interface.feedback.info.normal.background}"
          },
          "success": {
            "$type": "other",
            "$value": "{semantic.color.interface.feedback.success.normal.background}"
          },
          "warning": {
            "$type": "other",
            "$value": "{semantic.color.interface.feedback.warning.normal.background}"
          },
          "danger": {
            "$type": "other",
            "$value": "{semantic.color.interface.feedback.danger.normal.background}"
          }
        }
      }
    },
    "level": {
      "oneMinus": {
        "$type": "boxShadow",
        "$value": {
          "x": "{depth.elements.distance.flat}",
          "y": "{depth.elements.distance.flat}",
          "blur": "{depth.elements.distance.micro}",
          "spread": "{depth.elements.proximity.flat}",
          "color": "#0000001a",
          "type": "{depth.elements.position.inner}"
        },
        "$description": "Token de Profundidade para nível negativo interno, usado para dar senso de elementos com conteúdo interno (como formulários)."
      },
      "zero": {
        "$type": "boxShadow",
        "$value": {
          "x": "{depth.elements.distance.flat}",
          "y": "{depth.elements.distance.flat}",
          "blur": "{depth.elements.distance.micro}",
          "spread": "{depth.elements.proximity.flat}",
          "color": "#000000FF"
        },
        "$description": "Esse é o token de valor zero para profundidade. Normalmente ele é invocado em todos os componentes que possam usar um componente Box como agrupador. Motivo: isso facilita criar animações de relevo quando outros agrupadores de níveis diferentes são chamados."
      },
      "one": {
        "$type": "boxShadow",
        "$value": {
          "x": "{depth.elements.distance.flat}",
          "y": "{depth.elements.distance.flat}",
          "blur": "{depth.elements.distance.micro}",
          "spread": "{depth.elements.proximity.flat}",
          "color": "#0000001a",
          "type": "{depth.elements.position.outter}"
        }
      },
      "two": {
        "description": "",
        "$type": "boxShadow",
        "$value": {
          "x": "{depth.elements.distance.flat}",
          "y": "{depth.elements.distance.flat}",
          "blur": "{depth.elements.distance.extraSmall}",
          "spread": "{depth.elements.proximity.close}",
          "color": "#0000001a",
          "type": "{depth.elements.position.outter}"
        }
      },
      "three": {
        "description": "",
        "$type": "boxShadow",
        "$value": {
          "x": "{depth.elements.distance.flat}",
          "y": "{depth.elements.distance.flat}",
          "blur": "{depth.elements.distance.medium}",
          "spread": "{depth.elements.proximity.medium}",
          "color": "#0000001a",
          "type": "{depth.elements.position.outter}"
        }
      },
      "four": {
        "description": "",
        "$type": "boxShadow",
        "$value": {
          "x": "{depth.elements.distance.flat}",
          "y": "{depth.elements.distance.flat}",
          "blur": "{depth.elements.distance.large}",
          "spread": "{depth.elements.proximity.close}",
          "color": "#0000001a",
          "type": "{depth.elements.position.outter}"
        }
      },
      "five": {
        "description": "",
        "$type": "boxShadow",
        "$value": {
          "x": "{depth.elements.distance.flat}",
          "y": "{depth.elements.distance.flat}",
          "blur": "{depth.elements.distance.extraLarge}",
          "spread": "{depth.elements.proximity.close}",
          "color": "#0000001a",
          "type": "{depth.elements.position.outter}"
        }
      },
      "six": {
        "description": "",
        "$type": "boxShadow",
        "$value": {
          "x": "{depth.elements.distance.flat}",
          "y": "{depth.elements.distance.flat}",
          "blur": "{depth.elements.distance.mega}",
          "spread": "{depth.elements.proximity.close}",
          "color": "#0000001a",
          "type": "{depth.elements.position.outter}"
        }
      }
    }
  }
}